{
    "HP": {
        "training_loop": "LCWATrainingLoop",
        "dataset_kwargs": {
            "create_inverse_triples": true
        },
        "embedding_dim": 256,
        "random_seed": 1996,
        "model_kwargs": {},
        "evaluator_filtered": true,
        "loss": "CrossEntropyLoss",
        "loss_kwargs": {
            "reduction": "mean"
        },
        "regularizer": "NoRegularizer",
        "regularizer_kwargs": null,
        "optimizer": "Adam",
        "optimizer_kwargs": {
            "lr": 0.007525067744232913,
            "weight_decay": 0.0
        },
        "num_epochs": 151,
        "batch_size": 256,
        "label_smoothing": 0.08094657004944494,
        "negative_sampler": null,
        "negative_sampler_kwargs": null,
        "model": "ComplEx"
    },
    "dataset": "FB15k",
    "model": "ComplEx",
    "results": {
        "head": {
            "optimistic": {
                "inverse_harmonic_mean_rank": 0.5319715660527439,
                "adjusted_arithmetic_mean_rank": 0.028464812915433665,
                "inverse_geometric_mean_rank": 0.1714062120390672,
                "variance": 1097468.2078584018,
                "arithmetic_mean_rank": 209.69313199370248,
                "median_rank": 2.0,
                "inverse_median_rank": 0.5,
                "z_arithmetic_mean_rank": 408.62332552755515,
                "adjusted_geometric_mean_rank_index": 0.9991072750911769,
                "z_geometric_mean_rank": 243.23280985933786,
                "adjusted_inverse_harmonic_mean_rank": 0.5316474474936651,
                "count": 59071.0,
                "standard_deviation": 1047.6011683166462,
                "inverse_arithmetic_mean_rank": 0.004768873403207274,
                "geometric_mean_rank": 5.834094272919807,
                "adjusted_arithmetic_mean_rank_index": 0.9716670861198827,
                "median_absolute_deviation": 1.482602218505602,
                "z_inverse_harmonic_mean_rank": 12232.113117005762,
                "harmonic_mean_rank": 1.8797997182820334,
                "hits_at_1": 0.44170574393526435,
                "hits_at_3": 0.5839921450457923,
                "hits_at_5": 0.6364713649675814,
                "hits_at_10": 0.6965346786070999,
                "z_hits_at_k": 6485.997119080568,
                "adjusted_hits_at_k": 0.696328065167323
            },
            "realistic": {
                "inverse_harmonic_mean_rank": 0.5319715738296509,
                "adjusted_arithmetic_mean_rank": 0.028464812711742945,
                "inverse_geometric_mean_rank": 0.17140619456768036,
                "variance": 1097468.125,
                "arithmetic_mean_rank": 209.69313049316406,
                "median_rank": 2.0,
                "inverse_median_rank": 0.5,
                "z_arithmetic_mean_rank": 408.62332561322654,
                "adjusted_geometric_mean_rank_index": 0.9991072749566797,
                "z_geometric_mean_rank": 243.2328098265945,
                "adjusted_inverse_harmonic_mean_rank": 0.5316474552759578,
                "count": 59071.0,
                "standard_deviation": 1047.60107421875,
                "inverse_arithmetic_mean_rank": 0.004768873564898968,
                "geometric_mean_rank": 5.834095001220703,
                "adjusted_arithmetic_mean_rank_index": 0.9716670863236011,
                "median_absolute_deviation": 1.482602218505602,
                "z_inverse_harmonic_mean_rank": 12232.113296060294,
                "harmonic_mean_rank": 1.8797996908011898,
                "hits_at_1": 0.44170574393526435,
                "hits_at_3": 0.5839921450457923,
                "hits_at_5": 0.6364713649675814,
                "hits_at_10": 0.6965346786070999,
                "z_hits_at_k": 6485.997119080568,
                "adjusted_hits_at_k": 0.696328065167323
            },
            "pessimistic": {
                "inverse_harmonic_mean_rank": 0.5319715628790613,
                "adjusted_arithmetic_mean_rank": 0.028464817511431338,
                "inverse_geometric_mean_rank": 0.17140616810570355,
                "variance": 1097468.2182057365,
                "arithmetic_mean_rank": 209.69316585126373,
                "median_rank": 2.0,
                "inverse_median_rank": 0.5,
                "z_arithmetic_mean_rank": 408.6233235944992,
                "adjusted_geometric_mean_rank_index": 0.9991072748150276,
                "z_geometric_mean_rank": 243.23280979210926,
                "adjusted_inverse_harmonic_mean_rank": 0.5316474443177848,
                "count": 59071.0,
                "standard_deviation": 1047.601173255231,
                "inverse_arithmetic_mean_rank": 0.004768872633213542,
                "geometric_mean_rank": 5.834095768264975,
                "adjusted_arithmetic_mean_rank_index": 0.9716670815232611,
                "median_absolute_deviation": 1.482602218505602,
                "z_inverse_harmonic_mean_rank": 12232.113043935295,
                "harmonic_mean_rank": 1.879799729496707,
                "hits_at_1": 0.44170574393526435,
                "hits_at_3": 0.5839921450457923,
                "hits_at_5": 0.6364713649675814,
                "hits_at_10": 0.6965346786070999,
                "z_hits_at_k": 6485.997119080568,
                "adjusted_hits_at_k": 0.696328065167323
            }
        },
        "tail": {
            "optimistic": {
                "inverse_harmonic_mean_rank": 0.5980780867921736,
                "adjusted_arithmetic_mean_rank": 0.021172655356437507,
                "inverse_geometric_mean_rank": 0.25147265560325627,
                "variance": 912835.4214648309,
                "arithmetic_mean_rank": 156.82492255082866,
                "median_rank": 1.0,
                "inverse_median_rank": 1.0,
                "z_arithmetic_mean_rank": 411.81179559436015,
                "adjusted_geometric_mean_rank_index": 0.9994534705359277,
                "z_geometric_mean_rank": 243.31519480432488,
                "adjusted_inverse_harmonic_mean_rank": 0.5978012742549182,
                "count": 59071.0,
                "standard_deviation": 955.4242102149343,
                "inverse_arithmetic_mean_rank": 0.006376537502678435,
                "geometric_mean_rank": 3.976575495260532,
                "adjusted_arithmetic_mean_rank_index": 0.9789595122354433,
                "median_absolute_deviation": 0.0,
                "z_inverse_harmonic_mean_rank": 13796.314521362827,
                "harmonic_mean_rank": 1.6720224701151616,
                "hits_at_1": 0.5042914458871528,
                "hits_at_3": 0.6534678607099931,
                "hits_at_5": 0.7099253440774661,
                "hits_at_10": 0.772883479202993,
                "z_hits_at_k": 7219.769437796291,
                "adjusted_hits_at_k": 0.7727297938973908
            },
            "realistic": {
                "inverse_harmonic_mean_rank": 0.5980780124664307,
                "adjusted_arithmetic_mean_rank": 0.021172655100390105,
                "inverse_geometric_mean_rank": 0.2514726221561432,
                "variance": 912835.5,
                "arithmetic_mean_rank": 156.82492065429688,
                "median_rank": 1.0,
                "inverse_median_rank": 1.0,
                "z_arithmetic_mean_rank": 411.81179570208434,
                "adjusted_geometric_mean_rank_index": 0.9994534704267534,
                "z_geometric_mean_rank": 243.31519477774657,
                "adjusted_inverse_harmonic_mean_rank": 0.5978011998779855,
                "count": 59071.0,
                "standard_deviation": 955.4242553710938,
                "inverse_arithmetic_mean_rank": 0.006376537494361401,
                "geometric_mean_rank": 3.976576089859009,
                "adjusted_arithmetic_mean_rank_index": 0.9789595124915254,
                "median_absolute_deviation": 0.0,
                "z_inverse_harmonic_mean_rank": 13796.312804860036,
                "harmonic_mean_rank": 1.6720226779046299,
                "hits_at_1": 0.5042914458871528,
                "hits_at_3": 0.6534678607099931,
                "hits_at_5": 0.7099253440774661,
                "hits_at_10": 0.772883479202993,
                "z_hits_at_k": 7219.769437796291,
                "adjusted_hits_at_k": 0.7727297938973908
            },
            "pessimistic": {
                "inverse_harmonic_mean_rank": 0.5980780867921736,
                "adjusted_arithmetic_mean_rank": 0.021172655356437507,
                "inverse_geometric_mean_rank": 0.25147265560325627,
                "variance": 912835.4214648309,
                "arithmetic_mean_rank": 156.82492255082866,
                "median_rank": 1.0,
                "inverse_median_rank": 1.0,
                "z_arithmetic_mean_rank": 411.81179559436015,
                "adjusted_geometric_mean_rank_index": 0.9994534705359277,
                "z_geometric_mean_rank": 243.31519480432488,
                "adjusted_inverse_harmonic_mean_rank": 0.5978012742549182,
                "count": 59071.0,
                "standard_deviation": 955.4242102149343,
                "inverse_arithmetic_mean_rank": 0.006376537502678435,
                "geometric_mean_rank": 3.976575495260532,
                "adjusted_arithmetic_mean_rank_index": 0.9789595122354433,
                "median_absolute_deviation": 0.0,
                "z_inverse_harmonic_mean_rank": 13796.314521362827,
                "harmonic_mean_rank": 1.6720224701151616,
                "hits_at_1": 0.5042914458871528,
                "hits_at_3": 0.6534678607099931,
                "hits_at_5": 0.7099253440774661,
                "hits_at_10": 0.772883479202993,
                "z_hits_at_k": 7219.769437796291,
                "adjusted_hits_at_k": 0.7727297938973908
            }
        },
        "both": {
            "optimistic": {
                "inverse_harmonic_mean_rank": 0.5650248264224589,
                "adjusted_arithmetic_mean_rank": 0.024808811289885227,
                "inverse_geometric_mean_rank": 0.20761496894096795,
                "variance": 1005850.57655404,
                "arithmetic_mean_rank": 183.25902727226557,
                "median_rank": 2.0,
                "inverse_median_rank": 0.5,
                "z_arithmetic_mean_rank": 580.1391191862001,
                "adjusted_geometric_mean_rank_index": 0.9992972043924019,
                "z_geometric_mean_rank": 344.0716686056886,
                "adjusted_inverse_harmonic_mean_rank": 0.5647244236236109,
                "count": 118142.0,
                "standard_deviation": 1002.921022091989,
                "inverse_arithmetic_mean_rank": 0.005456757109783808,
                "geometric_mean_rank": 4.816608383783417,
                "adjusted_arithmetic_mean_rank_index": 0.9753232237326969,
                "median_absolute_deviation": 1.482602218505602,
                "z_inverse_harmonic_mean_rank": 18403.16661475626,
                "harmonic_mean_rank": 1.7698337369202926,
                "hits_at_1": 0.47299859491120855,
                "hits_at_3": 0.6187300028778927,
                "hits_at_5": 0.6731983545225237,
                "hits_at_10": 0.7347090789050464,
                "z_hits_at_k": 9690.634011423348,
                "adjusted_hits_at_k": 0.7345290090607343
            },
            "realistic": {
                "inverse_harmonic_mean_rank": 0.5650247931480408,
                "adjusted_arithmetic_mean_rank": 0.02480881002711062,
                "inverse_geometric_mean_rank": 0.207614928483963,
                "variance": 1005850.5,
                "arithmetic_mean_rank": 183.25901794433594,
                "median_rank": 2.0,
                "inverse_median_rank": 0.5,
                "z_arithmetic_mean_rank": 580.139119937422,
                "adjusted_geometric_mean_rank_index": 0.9992972042084729,
                "z_geometric_mean_rank": 344.07166854235936,
                "adjusted_inverse_harmonic_mean_rank": 0.5647243903262127,
                "count": 118142.0,
                "standard_deviation": 1002.9209594726562,
                "inverse_arithmetic_mean_rank": 0.005456757266074419,
                "geometric_mean_rank": 4.8166093826293945,
                "adjusted_arithmetic_mean_rank_index": 0.9753232249956424,
                "median_absolute_deviation": 1.482602218505602,
                "z_inverse_harmonic_mean_rank": 18403.16552966495,
                "harmonic_mean_rank": 1.7698338411461396,
                "hits_at_1": 0.47299859491120855,
                "hits_at_3": 0.6187300028778927,
                "hits_at_5": 0.6731983545225237,
                "hits_at_10": 0.7347090789050464,
                "z_hits_at_k": 9690.634011423348,
                "adjusted_hits_at_k": 0.7345290090607343
            },
            "pessimistic": {
                "inverse_harmonic_mean_rank": 0.5650248248356176,
                "adjusted_arithmetic_mean_rank": 0.024808813581630035,
                "inverse_geometric_mean_rank": 0.2076149423339261,
                "variance": 1005850.5826227021,
                "arithmetic_mean_rank": 183.2590442010462,
                "median_rank": 2.0,
                "inverse_median_rank": 0.5,
                "z_arithmetic_mean_rank": 580.1391178228461,
                "adjusted_geometric_mean_rank_index": 0.9992972042787358,
                "z_geometric_mean_rank": 344.0716685665518,
                "adjusted_inverse_harmonic_mean_rank": 0.5647244220356736,
                "count": 118142.0,
                "standard_deviation": 1002.9210251174826,
                "inverse_arithmetic_mean_rank": 0.005456756605709128,
                "geometric_mean_rank": 4.816609001059319,
                "adjusted_arithmetic_mean_rank_index": 0.9753232214406418,
                "median_absolute_deviation": 1.482602218505602,
                "z_inverse_harmonic_mean_rank": 18403.166563008766,
                "harmonic_mean_rank": 1.7698337418907737,
                "hits_at_1": 0.47299859491120855,
                "hits_at_3": 0.6187300028778927,
                "hits_at_5": 0.6731983545225237,
                "hits_at_10": 0.7347090789050464,
                "z_hits_at_k": 9690.634011423348,
                "adjusted_hits_at_k": 0.7345290090607343
            }
        }
    }
}